rest_access/__init__.py
rest_access/access.py
django_rest_access-0.0.3.dist-info/LICENSE
django_rest_access-0.0.3.dist-info/METADATA
django_rest_access-0.0.3.dist-info/WHEEL
django_rest_access-0.0.3.dist-info/top_level.txt
django_rest_access-0.0.3.dist-info/RECORD
